{
  "converted_at": 1520475815,
  "weight_encoding": "eightbit",
  "memory_layout": {
    "static": {
      "size": 62777984,
      "allocations": {
        "a387": {
          "name": "a387",
          "offset": 59411584,
          "size": 150528
        },
        "a389": {
          "name": "a389",
          "offset": 59261056,
          "size": 150528
        },
        "a390": {
          "name": "a390",
          "offset": 24526720,
          "size": 1843968
        },
        "a541": {
          "name": "a541",
          "offset": 36205184,
          "size": 802816
        },
        "a393": {
          "name": "a393",
          "offset": 56852608,
          "size": 200704
        },
        "a394": {
          "name": "a394",
          "offset": 57856128,
          "size": 200704
        },
        "a395": {
          "name": "a395",
          "offset": 58658944,
          "size": 200704
        },
        "a397": {
          "name": "a397",
          "offset": 59060352,
          "size": 200704
        },
        "a398": {
          "name": "a398",
          "offset": 58859648,
          "size": 200704
        },
        "a399": {
          "name": "a399",
          "offset": 58458240,
          "size": 200704
        },
        "a400": {
          "name": "a400",
          "offset": 26370688,
          "size": 1806336
        },
        "a542": {
          "name": "a542",
          "offset": 57655424,
          "size": 200704
        },
        "a403": {
          "name": "a403",
          "offset": 38613632,
          "size": 802816
        },
        "a396": {
          "name": "a396",
          "offset": 35402368,
          "size": 802816
        },
        "a404": {
          "name": "a404",
          "offset": 40219264,
          "size": 802816
        },
        "a405": {
          "name": "a405",
          "offset": 41022080,
          "size": 802816
        },
        "a543": {
          "name": "a543",
          "offset": 56451200,
          "size": 200704
        },
        "a408": {
          "name": "a408",
          "offset": 28177024,
          "size": 1806336
        },
        "a544": {
          "name": "a544",
          "offset": 58257536,
          "size": 200704
        },
        "a411": {
          "name": "a411",
          "offset": 37810816,
          "size": 802816
        },
        "a546": {
          "name": "a546",
          "offset": 43430528,
          "size": 802816
        },
        "a413": {
          "name": "a413",
          "offset": 39416448,
          "size": 802816
        },
        "a414": {
          "name": "a414",
          "offset": 57053312,
          "size": 200704
        },
        "a415": {
          "name": "a415",
          "offset": 56651904,
          "size": 200704
        },
        "a416": {
          "name": "a416",
          "offset": 29983360,
          "size": 1806336
        },
        "a545": {
          "name": "a545",
          "offset": 57454720,
          "size": 200704
        },
        "a419": {
          "name": "a419",
          "offset": 42627712,
          "size": 802816
        },
        "a421": {
          "name": "a421",
          "offset": 41824896,
          "size": 802816
        },
        "a422": {
          "name": "a422",
          "offset": 58056832,
          "size": 200704
        },
        "a424": {
          "name": "a424",
          "offset": 37008000,
          "size": 802816
        },
        "a425": {
          "name": "a425",
          "offset": 57254016,
          "size": 200704
        },
        "a547": {
          "name": "a547",
          "offset": 61569152,
          "size": 100352
        },
        "a428": {
          "name": "a428",
          "offset": 34499200,
          "size": 903168
        },
        "a429": {
          "name": "a429",
          "offset": 61368448,
          "size": 100352
        },
        "a430": {
          "name": "a430",
          "offset": 61268096,
          "size": 100352
        },
        "a431": {
          "name": "a431",
          "offset": 50956928,
          "size": 401408
        },
        "a423": {
          "name": "a423",
          "offset": 50555520,
          "size": 401408
        },
        "a432": {
          "name": "a432",
          "offset": 51358336,
          "size": 401408
        },
        "a433": {
          "name": "a433",
          "offset": 51759744,
          "size": 401408
        },
        "a548": {
          "name": "a548",
          "offset": 61468800,
          "size": 100352
        },
        "a436": {
          "name": "a436",
          "offset": 33596032,
          "size": 903168
        },
        "a437": {
          "name": "a437",
          "offset": 61167744,
          "size": 100352
        },
        "a438": {
          "name": "a438",
          "offset": 59562112,
          "size": 100352
        },
        "a439": {
          "name": "a439",
          "offset": 48548480,
          "size": 401408
        },
        "a551": {
          "name": "a551",
          "offset": 46942848,
          "size": 401408
        },
        "a441": {
          "name": "a441",
          "offset": 50154112,
          "size": 401408
        },
        "a549": {
          "name": "a549",
          "offset": 60967040,
          "size": 100352
        },
        "a444": {
          "name": "a444",
          "offset": 31789696,
          "size": 903168
        },
        "a550": {
          "name": "a550",
          "offset": 60766336,
          "size": 100352
        },
        "a447": {
          "name": "a447",
          "offset": 47344256,
          "size": 401408
        },
        "a449": {
          "name": "a449",
          "offset": 47745664,
          "size": 401408
        },
        "a552": {
          "name": "a552",
          "offset": 60364928,
          "size": 100352
        },
        "a452": {
          "name": "a452",
          "offset": 32692864,
          "size": 903168
        },
        "a553": {
          "name": "a553",
          "offset": 61067392,
          "size": 100352
        },
        "a455": {
          "name": "a455",
          "offset": 49752704,
          "size": 401408
        },
        "a456": {
          "name": "a456",
          "offset": 48147072,
          "size": 401408
        },
        "a457": {
          "name": "a457",
          "offset": 48949888,
          "size": 401408
        },
        "a458": {
          "name": "a458",
          "offset": 60565632,
          "size": 100352
        },
        "a460": {
          "name": "a460",
          "offset": 49351296,
          "size": 401408
        },
        "a461": {
          "name": "a461",
          "offset": 60465280,
          "size": 100352
        },
        "a554": {
          "name": "a554",
          "offset": 61769856,
          "size": 50176
        },
        "a464": {
          "name": "a464",
          "offset": 44684928,
          "size": 451584
        },
        "a555": {
          "name": "a555",
          "offset": 61820032,
          "size": 50176
        },
        "a467": {
          "name": "a467",
          "offset": 54644864,
          "size": 200704
        },
        "a459": {
          "name": "a459",
          "offset": 54845568,
          "size": 200704
        },
        "a557": {
          "name": "a557",
          "offset": 53641344,
          "size": 200704
        },
        "a469": {
          "name": "a469",
          "offset": 53239936,
          "size": 200704
        },
        "a556": {
          "name": "a556",
          "offset": 62070912,
          "size": 50176
        },
        "a472": {
          "name": "a472",
          "offset": 44233344,
          "size": 451584
        },
        "a473": {
          "name": "a473",
          "offset": 62221440,
          "size": 50176
        },
        "a474": {
          "name": "a474",
          "offset": 62020736,
          "size": 50176
        },
        "a475": {
          "name": "a475",
          "offset": 55246976,
          "size": 200704
        },
        "a477": {
          "name": "a477",
          "offset": 53039232,
          "size": 200704
        },
        "a478": {
          "name": "a478",
          "offset": 61719680,
          "size": 50176
        },
        "a479": {
          "name": "a479",
          "offset": 62121088,
          "size": 50176
        },
        "a480": {
          "name": "a480",
          "offset": 46039680,
          "size": 451584
        },
        "a558": {
          "name": "a558",
          "offset": 62171264,
          "size": 50176
        },
        "a483": {
          "name": "a483",
          "offset": 56250496,
          "size": 200704
        },
        "a484": {
          "name": "a484",
          "offset": 54243456,
          "size": 200704
        },
        "a485": {
          "name": "a485",
          "offset": 53842048,
          "size": 200704
        },
        "a559": {
          "name": "a559",
          "offset": 61669504,
          "size": 50176
        },
        "a488": {
          "name": "a488",
          "offset": 45588096,
          "size": 451584
        },
        "a560": {
          "name": "a560",
          "offset": 62321792,
          "size": 50176
        },
        "a491": {
          "name": "a491",
          "offset": 55849088,
          "size": 200704
        },
        "a492": {
          "name": "a492",
          "offset": 53440640,
          "size": 200704
        },
        "a493": {
          "name": "a493",
          "offset": 54042752,
          "size": 200704
        },
        "a561": {
          "name": "a561",
          "offset": 62371968,
          "size": 50176
        },
        "a496": {
          "name": "a496",
          "offset": 45136512,
          "size": 451584
        },
        "a497": {
          "name": "a497",
          "offset": 62422144,
          "size": 50176
        },
        "a498": {
          "name": "a498",
          "offset": 62271616,
          "size": 50176
        },
        "a499": {
          "name": "a499",
          "offset": 52838528,
          "size": 200704
        },
        "a564": {
          "name": "a564",
          "offset": 56049792,
          "size": 200704
        },
        "a501": {
          "name": "a501",
          "offset": 55447680,
          "size": 200704
        },
        "a562": {
          "name": "a562",
          "offset": 62472320,
          "size": 50176
        },
        "a504": {
          "name": "a504",
          "offset": 46491264,
          "size": 451584
        },
        "a563": {
          "name": "a563",
          "offset": 61920384,
          "size": 50176
        },
        "a507": {
          "name": "a507",
          "offset": 54444160,
          "size": 200704
        },
        "a509": {
          "name": "a509",
          "offset": 55046272,
          "size": 200704
        },
        "a510": {
          "name": "a510",
          "offset": 61970560,
          "size": 50176
        },
        "a512": {
          "name": "a512",
          "offset": 55648384,
          "size": 200704
        },
        "a513": {
          "name": "a513",
          "offset": 61870208,
          "size": 50176
        },
        "a514": {
          "name": "a514",
          "offset": 62547584,
          "size": 25088
        },
        "a515": {
          "name": "a515",
          "offset": 62673024,
          "size": 25088
        },
        "a516": {
          "name": "a516",
          "offset": 52386944,
          "size": 225792
        },
        "a565": {
          "name": "a565",
          "offset": 62748288,
          "size": 25088
        },
        "a519": {
          "name": "a519",
          "offset": 60866688,
          "size": 100352
        },
        "a511": {
          "name": "a511",
          "offset": 60264576,
          "size": 100352
        },
        "a520": {
          "name": "a520",
          "offset": 59762816,
          "size": 100352
        },
        "a521": {
          "name": "a521",
          "offset": 59863168,
          "size": 100352
        },
        "a566": {
          "name": "a566",
          "offset": 62572672,
          "size": 25088
        },
        "a524": {
          "name": "a524",
          "offset": 52612736,
          "size": 225792
        },
        "a525": {
          "name": "a525",
          "offset": 62723200,
          "size": 25088
        },
        "a526": {
          "name": "a526",
          "offset": 62698112,
          "size": 25088
        },
        "a527": {
          "name": "a527",
          "offset": 59963520,
          "size": 100352
        },
        "a528": {
          "name": "a528",
          "offset": 60164224,
          "size": 100352
        },
        "a529": {
          "name": "a529",
          "offset": 60665984,
          "size": 100352
        },
        "a530": {
          "name": "a530",
          "offset": 62597760,
          "size": 25088
        },
        "a531": {
          "name": "a531",
          "offset": 62522496,
          "size": 25088
        },
        "a532": {
          "name": "a532",
          "offset": 52161152,
          "size": 225792
        },
        "a533": {
          "name": "a533",
          "offset": 62622848,
          "size": 25088
        },
        "a534": {
          "name": "a534",
          "offset": 62647936,
          "size": 25088
        },
        "a535": {
          "name": "a535",
          "offset": 59662464,
          "size": 100352
        },
        "a536": {
          "name": "a536",
          "offset": 60063872,
          "size": 100352
        },
        "a537": {
          "name": "a537",
          "offset": 62773376,
          "size": 2048
        },
        "a567": {
          "name": "a567",
          "offset": 62775424,
          "size": 2048
        },
        "a568": {
          "name": "a568",
          "offset": 62777472,
          "size": 512
        },
        "a283": {
          "name": "a283",
          "offset": 0,
          "size": 9408
        },
        "a284": {
          "name": "a284",
          "offset": 9408,
          "size": 64
        },
        "a285": {
          "name": "a285",
          "offset": 9472,
          "size": 16384
        },
        "a286": {
          "name": "a286",
          "offset": 25856,
          "size": 4096
        },
        "a287": {
          "name": "a287",
          "offset": 29952,
          "size": 64
        },
        "a288": {
          "name": "a288",
          "offset": 30016,
          "size": 36864
        },
        "a289": {
          "name": "a289",
          "offset": 66880,
          "size": 64
        },
        "a290": {
          "name": "a290",
          "offset": 66944,
          "size": 16384
        },
        "a291": {
          "name": "a291",
          "offset": 83328,
          "size": 256
        },
        "a292": {
          "name": "a292",
          "offset": 83584,
          "size": 16384
        },
        "a293": {
          "name": "a293",
          "offset": 99968,
          "size": 64
        },
        "a294": {
          "name": "a294",
          "offset": 100032,
          "size": 36864
        },
        "a295": {
          "name": "a295",
          "offset": 136896,
          "size": 64
        },
        "a296": {
          "name": "a296",
          "offset": 136960,
          "size": 16384
        },
        "a297": {
          "name": "a297",
          "offset": 153344,
          "size": 256
        },
        "a298": {
          "name": "a298",
          "offset": 153600,
          "size": 16384
        },
        "a299": {
          "name": "a299",
          "offset": 169984,
          "size": 64
        },
        "a300": {
          "name": "a300",
          "offset": 170048,
          "size": 36864
        },
        "a301": {
          "name": "a301",
          "offset": 206912,
          "size": 64
        },
        "a302": {
          "name": "a302",
          "offset": 206976,
          "size": 16384
        },
        "a303": {
          "name": "a303",
          "offset": 223360,
          "size": 256
        },
        "a304": {
          "name": "a304",
          "offset": 223616,
          "size": 131072
        },
        "a305": {
          "name": "a305",
          "offset": 354688,
          "size": 32768
        },
        "a306": {
          "name": "a306",
          "offset": 387456,
          "size": 128
        },
        "a307": {
          "name": "a307",
          "offset": 387584,
          "size": 147456
        },
        "a308": {
          "name": "a308",
          "offset": 535040,
          "size": 128
        },
        "a309": {
          "name": "a309",
          "offset": 535168,
          "size": 65536
        },
        "a310": {
          "name": "a310",
          "offset": 600704,
          "size": 512
        },
        "a311": {
          "name": "a311",
          "offset": 601216,
          "size": 65536
        },
        "a312": {
          "name": "a312",
          "offset": 666752,
          "size": 128
        },
        "a313": {
          "name": "a313",
          "offset": 666880,
          "size": 147456
        },
        "a314": {
          "name": "a314",
          "offset": 814336,
          "size": 128
        },
        "a315": {
          "name": "a315",
          "offset": 814464,
          "size": 65536
        },
        "a316": {
          "name": "a316",
          "offset": 880000,
          "size": 512
        },
        "a317": {
          "name": "a317",
          "offset": 880512,
          "size": 65536
        },
        "a318": {
          "name": "a318",
          "offset": 946048,
          "size": 128
        },
        "a319": {
          "name": "a319",
          "offset": 946176,
          "size": 147456
        },
        "a320": {
          "name": "a320",
          "offset": 1093632,
          "size": 128
        },
        "a321": {
          "name": "a321",
          "offset": 1093760,
          "size": 65536
        },
        "a322": {
          "name": "a322",
          "offset": 1159296,
          "size": 512
        },
        "a323": {
          "name": "a323",
          "offset": 1159808,
          "size": 65536
        },
        "a324": {
          "name": "a324",
          "offset": 1225344,
          "size": 128
        },
        "a325": {
          "name": "a325",
          "offset": 1225472,
          "size": 147456
        },
        "a326": {
          "name": "a326",
          "offset": 1372928,
          "size": 128
        },
        "a327": {
          "name": "a327",
          "offset": 1373056,
          "size": 65536
        },
        "a328": {
          "name": "a328",
          "offset": 1438592,
          "size": 512
        },
        "a329": {
          "name": "a329",
          "offset": 1439104,
          "size": 524288
        },
        "a330": {
          "name": "a330",
          "offset": 1963392,
          "size": 131072
        },
        "a331": {
          "name": "a331",
          "offset": 2094464,
          "size": 256
        },
        "a332": {
          "name": "a332",
          "offset": 2094720,
          "size": 589824
        },
        "a333": {
          "name": "a333",
          "offset": 2684544,
          "size": 256
        },
        "a334": {
          "name": "a334",
          "offset": 2684800,
          "size": 262144
        },
        "a335": {
          "name": "a335",
          "offset": 2946944,
          "size": 1024
        },
        "a336": {
          "name": "a336",
          "offset": 2947968,
          "size": 262144
        },
        "a337": {
          "name": "a337",
          "offset": 3210112,
          "size": 256
        },
        "a338": {
          "name": "a338",
          "offset": 3210368,
          "size": 589824
        },
        "a339": {
          "name": "a339",
          "offset": 3800192,
          "size": 256
        },
        "a340": {
          "name": "a340",
          "offset": 3800448,
          "size": 262144
        },
        "a341": {
          "name": "a341",
          "offset": 4062592,
          "size": 1024
        },
        "a342": {
          "name": "a342",
          "offset": 4063616,
          "size": 262144
        },
        "a343": {
          "name": "a343",
          "offset": 4325760,
          "size": 256
        },
        "a344": {
          "name": "a344",
          "offset": 4326016,
          "size": 589824
        },
        "a345": {
          "name": "a345",
          "offset": 4915840,
          "size": 256
        },
        "a346": {
          "name": "a346",
          "offset": 4916096,
          "size": 262144
        },
        "a347": {
          "name": "a347",
          "offset": 5178240,
          "size": 1024
        },
        "a348": {
          "name": "a348",
          "offset": 5179264,
          "size": 262144
        },
        "a349": {
          "name": "a349",
          "offset": 5441408,
          "size": 256
        },
        "a350": {
          "name": "a350",
          "offset": 5441664,
          "size": 589824
        },
        "a351": {
          "name": "a351",
          "offset": 6031488,
          "size": 256
        },
        "a352": {
          "name": "a352",
          "offset": 6031744,
          "size": 262144
        },
        "a353": {
          "name": "a353",
          "offset": 6293888,
          "size": 1024
        },
        "a354": {
          "name": "a354",
          "offset": 6294912,
          "size": 262144
        },
        "a355": {
          "name": "a355",
          "offset": 6557056,
          "size": 256
        },
        "a356": {
          "name": "a356",
          "offset": 6557312,
          "size": 589824
        },
        "a357": {
          "name": "a357",
          "offset": 7147136,
          "size": 256
        },
        "a358": {
          "name": "a358",
          "offset": 7147392,
          "size": 262144
        },
        "a359": {
          "name": "a359",
          "offset": 7409536,
          "size": 1024
        },
        "a360": {
          "name": "a360",
          "offset": 7410560,
          "size": 262144
        },
        "a361": {
          "name": "a361",
          "offset": 7672704,
          "size": 256
        },
        "a362": {
          "name": "a362",
          "offset": 7672960,
          "size": 589824
        },
        "a363": {
          "name": "a363",
          "offset": 8262784,
          "size": 256
        },
        "a364": {
          "name": "a364",
          "offset": 8263040,
          "size": 262144
        },
        "a365": {
          "name": "a365",
          "offset": 8525184,
          "size": 1024
        },
        "a366": {
          "name": "a366",
          "offset": 8526208,
          "size": 2097152
        },
        "a367": {
          "name": "a367",
          "offset": 10623360,
          "size": 524288
        },
        "a368": {
          "name": "a368",
          "offset": 11147648,
          "size": 512
        },
        "a369": {
          "name": "a369",
          "offset": 11148160,
          "size": 2359296
        },
        "a370": {
          "name": "a370",
          "offset": 13507456,
          "size": 512
        },
        "a371": {
          "name": "a371",
          "offset": 13507968,
          "size": 1048576
        },
        "a372": {
          "name": "a372",
          "offset": 14556544,
          "size": 2048
        },
        "a373": {
          "name": "a373",
          "offset": 14558592,
          "size": 1048576
        },
        "a374": {
          "name": "a374",
          "offset": 15607168,
          "size": 512
        },
        "a375": {
          "name": "a375",
          "offset": 15607680,
          "size": 2359296
        },
        "a376": {
          "name": "a376",
          "offset": 17966976,
          "size": 512
        },
        "a377": {
          "name": "a377",
          "offset": 17967488,
          "size": 1048576
        },
        "a378": {
          "name": "a378",
          "offset": 19016064,
          "size": 2048
        },
        "a379": {
          "name": "a379",
          "offset": 19018112,
          "size": 1048576
        },
        "a380": {
          "name": "a380",
          "offset": 20066688,
          "size": 512
        },
        "a381": {
          "name": "a381",
          "offset": 20067200,
          "size": 2359296
        },
        "a382": {
          "name": "a382",
          "offset": 22426496,
          "size": 512
        },
        "a383": {
          "name": "a383",
          "offset": 22427008,
          "size": 1048576
        },
        "a384": {
          "name": "a384",
          "offset": 23475584,
          "size": 2048
        },
        "a385": {
          "name": "a385",
          "offset": 23477632,
          "size": 1048576
        },
        "a386": {
          "name": "a386",
          "offset": 24526208,
          "size": 512
        }
      }
    },
    "dynamic": {
      "size": 0,
      "allocations": {}
    }
  },
  "placeholders": {},
  "unresolved_value_lists": [
    [],
    [],
    [],
    [],
    [],
    [],
    [],
    [],
    [],
    [],
    [],
    [],
    [],
    [],
    [],
    [],
    [],
    [],
    [],
    [],
    [],
    [],
    [],
    [],
    [],
    [],
    [],
    [],
    [],
    [],
    [],
    [],
    [],
    [],
    [],
    [],
    [],
    [],
    [],
    [],
    [],
    [],
    [],
    [],
    [],
    [],
    [],
    [],
    [],
    [],
    [],
    [],
    [],
    [],
    [],
    [],
    [],
    [],
    [],
    [],
    [],
    [],
    [],
    [],
    [],
    [],
    [],
    [],
    [],
    [],
    [],
    [],
    [],
    [],
    [],
    [],
    [],
    [],
    [],
    [],
    [],
    [],
    [],
    [],
    [],
    [],
    [],
    [],
    [],
    [],
    [],
    [],
    [],
    [],
    [],
    [],
    [],
    [],
    [],
    [],
    [],
    [],
    [],
    [],
    [],
    [],
    [],
    [],
    [],
    [],
    [],
    [],
    [],
    [],
    [],
    [],
    [],
    [],
    [],
    [],
    [],
    [],
    [],
    [],
    [],
    [],
    [],
    [],
    [],
    [],
    [],
    [],
    [],
    [],
    [],
    [],
    [],
    [],
    [],
    [],
    [],
    [],
    [],
    [],
    [],
    [],
    [],
    [],
    [],
    [],
    [],
    []
  ],
  "inputs": [
    "a387"
  ],
  "outputs": [
    "a568"
  ],
  "licenses": {
    "webdnn": "(C) Machine Intelligence Laboratory (The University of Tokyo), MIT License",
    "eigen": "(C) Eigen authors, MPL 2.0 License"
  }
}